semantic_code_mcp/__init__.py
semantic_code_mcp/__main__.py
semantic_code_mcp/app.py
semantic_code_mcp/cli.py
semantic_code_mcp/config.py
semantic_code_mcp/container.py
semantic_code_mcp/embedder.py
semantic_code_mcp/indexer.py
semantic_code_mcp/logging.py
semantic_code_mcp/profiling.py
semantic_code_mcp/protocols.py
semantic_code_mcp/server.py
semantic_code_mcp/chunkers/__init__.py
semantic_code_mcp/chunkers/base.py
semantic_code_mcp/chunkers/composite.py
semantic_code_mcp/chunkers/markdown.py
semantic_code_mcp/chunkers/python.py
semantic_code_mcp/chunkers/rust.py
semantic_code_mcp/models/__init__.py
semantic_code_mcp/models/domain.py
semantic_code_mcp/models/responses.py
semantic_code_mcp/services/__init__.py
semantic_code_mcp/services/index_service.py
semantic_code_mcp/services/search_service.py
semantic_code_mcp/storage/__init__.py
semantic_code_mcp/storage/cache.py
semantic_code_mcp/storage/lancedb.py
semantic_code_mcp-0.4.0.dist-info/METADATA
semantic_code_mcp-0.4.0.dist-info/WHEEL
semantic_code_mcp-0.4.0.dist-info/entry_points.txt
semantic_code_mcp-0.4.0.dist-info/RECORD
