Metadata-Version: 2.4
Name: semantic-code-mcp
Version: 0.4.0
Summary: Local MCP server for semantic code search
Requires-Python: >=3.14
Requires-Dist: lancedb>=0.27.0
Requires-Dist: mcp>=1.26.0
Requires-Dist: pandas>=3.0.0
Requires-Dist: pydantic-settings>=2.12.0
Requires-Dist: pydantic>=2.12.5
Requires-Dist: sentence-transformers>=5.2.0
Requires-Dist: structlog>=25.5.0
Requires-Dist: torch>=2.10.0
Requires-Dist: tree-sitter-markdown>=0.5.1
Requires-Dist: tree-sitter-python>=0.25.0
Requires-Dist: tree-sitter-rust>=0.24.0
Requires-Dist: tree-sitter>=0.25.2
